django_client_ip/__init__.py
django_client_ip/ip.py
django_client_ip-0.12.dist-info/LICENSE
django_client_ip-0.12.dist-info/METADATA
django_client_ip-0.12.dist-info/WHEEL
django_client_ip-0.12.dist-info/top_level.txt
django_client_ip-0.12.dist-info/RECORD
