Metadata-Version: 2.1
Name: django-client-ip
Version: 0.12
Summary: A Django middleware for retrieving client IP addresses and geolocation using ip-api.com
Home-page: https://github.com/cumulus13/django-client-ip
Author: Hadi Cahyadi
Author-email: cumulus13@gmail.com
License: MIT
Classifier: Framework :: Django
Classifier: Programming Language :: Python :: 3
Classifier: License :: OSI Approved :: MIT License
Classifier: Operating System :: OS Independent
License-File: LICENSE
Requires-Dist: Django (>=3.0)
Requires-Dist: requests
Requires-Dist: rich
